pygrammalecte/__init__.py
pygrammalecte/pygrammalecte.py
pygrammalecte-1.5.0.dist-info/METADATA
pygrammalecte-1.5.0.dist-info/WHEEL
pygrammalecte-1.5.0.dist-info/licenses/LICENSE
pygrammalecte-1.5.0.dist-info/RECORD
