Metadata-Version: 2.3
Name: pygrammalecte
Version: 1.5.0
Summary: Grammalecte, le correcteur grammatical en Python
Project-URL: Source code, https://github.com/vpoulailleau/pygrammalecte
Project-URL: Repository, https://github.com/vpoulailleau/pygrammalecte
Project-URL: homepage, https://github.com/vpoulailleau/pygrammalecte
Project-URL: documentation, https://github.com/vpoulailleau/pygrammalecte
Author-email: Vincent Poulailleau <vpoulailleau@gmail.com>
License: BSD-3-Clause
Keywords: french,grammalecte,grammar-checker,grammatical,linter
Classifier: Operating System :: OS Independent
Classifier: Programming Language :: Python :: 3.9
Classifier: Programming Language :: Python :: 3.10
Classifier: Programming Language :: Python :: 3.11
Classifier: Programming Language :: Python :: 3.12
Classifier: Programming Language :: Python :: 3.13
Requires-Python: >=3.9
Requires-Dist: pip>=23
Requires-Dist: requests>=2.20.0
